{
  "schemes" : [
    {
      "scrolling" : {
        "reverse" : {
          "vertical" : true
        },
        "acceleration" : {
          "vertical" : 1
        },
        "speed" : {
          "vertical" : 0
        },
        "distance" : {
          "vertical" : "auto"
        }
      },
      "if" : {
        "device" : {
          "vendorID" : "0x46d",
          "category" : "mouse",
          "productID" : "0xc52b",
          "productName" : "USB Receiver"
        }
      },
      "pointer" : {
        "disableAcceleration" : true
      },
      "buttons" : {
        "mappings" : [
          {
            "option" : false,
            "command" : false,
            "control" : false,
            "shift" : false,
            "button" : 2,
            "action" : "missionControl"
          },
          {
            "option" : false,
            "control" : false,
            "action" : "missionControl.spaceLeft",
            "shift" : false,
            "command" : false,
            "button" : 3
          },
          {
            "button" : 4,
            "command" : false,
            "control" : false,
            "shift" : false,
            "option" : false,
            "action" : "missionControl.spaceRight"
          }
        ],
        "universalBackForward" : true
      }
    },
    {
      "scrolling" : {
        "acceleration" : {
          "vertical" : 2
        },
        "reverse" : {
          "vertical" : true
        },
        "speed" : {
          "vertical" : 1.19
        }
      },
      "pointer" : {
        "disableAcceleration" : false,
        "acceleration" : 0,
        "speed" : 1
      },
      "if" : {
        "device" : {
          "productID" : "0xc049",
          "category" : "mouse",
          "vendorID" : "0x46d",
          "productName" : "USB Gaming Mouse"
        }
      },
      "buttons" : {
        "mappings" : [
          {
            "action" : "missionControl",
            "button" : 2,
            "command" : false,
            "option" : false,
            "shift" : false,
            "control" : false
          },
          {
            "command" : false,
            "shift" : false,
            "option" : false,
            "control" : false,
            "action" : "missionControl.spaceLeft",
            "button" : 3
          },
          {
            "option" : false,
            "button" : 4,
            "control" : false,
            "action" : "missionControl.spaceRight",
            "shift" : false,
            "command" : false
          }
        ],
        "universalBackForward" : true
      }
    }
  ],
  "$schema" : "https:\/\/schema.linearmouse.app\/0.10.0"
}